python_manta/libmanta_wrapper.so
python_manta/manta_python.py
python_manta/__init__.py
python_manta/libmanta_wrapper.h
python_manta-1.4.7.3.dist-info/RECORD
python_manta-1.4.7.3.dist-info/WHEEL
python_manta-1.4.7.3.dist-info/top_level.txt
python_manta-1.4.7.3.dist-info/METADATA
