Metadata-Version: 2.1
Name: python-manta
Version: 1.4.7.3
Summary: Python interface for the Manta Dota 2 replay parser
Author-email: Equilibrium Coach Team <contact@equilibrium-coach.com>
License: MIT
Project-URL: Homepage, https://github.com/DeepBlueCoding/python-manta
Project-URL: Repository, https://github.com/DeepBlueCoding/python-manta
Project-URL: Documentation, https://deepbluecoding.github.io/python-manta/
Project-URL: Bug Tracker, https://github.com/DeepBlueCoding/python-manta/issues
Keywords: dota2,replay,parser,gaming,esports,manta
Classifier: Development Status :: 3 - Alpha
Classifier: Intended Audience :: Developers
Classifier: License :: OSI Approved :: MIT License
Classifier: Programming Language :: Python :: 3
Classifier: Programming Language :: Python :: 3.8
Classifier: Programming Language :: Python :: 3.9
Classifier: Programming Language :: Python :: 3.10
Classifier: Programming Language :: Python :: 3.11
Classifier: Programming Language :: Python :: 3.12
Classifier: Programming Language :: Python :: 3.13
Classifier: Programming Language :: Go
Classifier: Topic :: Games/Entertainment
Classifier: Topic :: Software Development :: Libraries :: Python Modules
Requires-Python: >=3.8
Requires-Dist: pydantic>=2.0.0
Provides-Extra: build
Requires-Dist: cibuildwheel>=2.17.0; extra == "build"
Provides-Extra: dev
Requires-Dist: pytest>=7.0.0; extra == "dev"
Requires-Dist: pytest-cov>=4.0.0; extra == "dev"
Requires-Dist: black>=22.0.0; extra == "dev"
Requires-Dist: isort>=5.0.0; extra == "dev"
Requires-Dist: mypy>=1.0.0; extra == "dev"
